MANIFEST.in
README.md
setup.py
contrib/ketama.c
contrib/ketama.h
contrib/md5.c
contrib/md5.h
ketama/__init__.py
ketama/ketama.c
ketama/ketama.pyx
pyketama.egg-info/PKG-INFO
pyketama.egg-info/SOURCES.txt
pyketama.egg-info/dependency_links.txt
pyketama.egg-info/not-zip-safe
pyketama.egg-info/top_level.txt