Metadata-Version: 1.1
Name: pyketama
Version: 0.2.1
Summary: ketama consistent hashing in cython
Home-page: https://github.com/maralla/pyketama
Author: maralla
Author-email: maralla.ai@gmail.com
License: BSD
Keywords: python ketama consistent hash cython
Platform: UNKNOWN
Classifier: Topic :: Software Development
Classifier: Intended Audience :: Developers
Classifier: License :: OSI Approved :: BSD License
Classifier: Programming Language :: Python :: 2.7
Classifier: Programming Language :: Python :: 3.3
Classifier: Programming Language :: Python :: 3.4
